videocod/__init__.py
videocod/app.py
videocod/create_image2_to_video_15.py
videocod/create_image_to_video_15.py
videocod/create_task.py
videocod/create_text_to_video_15.py
videocod/create_video_reference.py
videocod/create_video_reference2_15.py
videocod/create_video_reference_15.py
videocod/credit.py
videocod/headtailimg2video.py
videocod/main.py
videocod/texttovideo.py
videocod/token_extractor.py
videocod/upload/__init__.py
videocod/upload/file_uploader.py
videocod/upload/file_uploader_with_etag.py
videocod/upload/finish_upload.py
videocod/utils/__init__.py
videocod/utils/auth.py
videocod/utils/delete_task.py
videocod/utils/delete_task_upscale.py
videocod/utils/email_utils.py
videocod/utils/fragment.py
videocod/utils/jwt_reader.py
videocod/utils/process_task.py
videocod/utils/process_task_upscale.py
videocod/utils/setup.py
videocod/utils/union.py
videocod/utils/upscale_task.py
videocod/utils/utils.py
videocod/utils/video_fragment.py
video_configuracion-1.2.0.dist-info/LICENSE
video_configuracion-1.2.0.dist-info/METADATA
video_configuracion-1.2.0.dist-info/WHEEL
video_configuracion-1.2.0.dist-info/top_level.txt
video_configuracion-1.2.0.dist-info/RECORD
